iot/edge/validator/__init__.py
iot/edge/validator/_exceptions.py
iot/edge/validator/_validator.py
iot/edge/validator/_version.py
iot_edge_validator-1.0.6.dist-info/METADATA
iot_edge_validator-1.0.6.dist-info/WHEEL
iot_edge_validator-1.0.6.dist-info/top_level.txt
iot_edge_validator-1.0.6.dist-info/RECORD
